oauth2tools/__init__.py
oauth2tools/exceptions.py
oauth2tools/jwt_helper.py
oauth2tools/oauth2tools.py
oauth2tools/oauth4cli.py
oauth2tools/tools.py
oauth2tools/templates/close_me.html
oauth2tools-0.9.1.dist-info/LICENSE
oauth2tools-0.9.1.dist-info/METADATA
oauth2tools-0.9.1.dist-info/WHEEL
oauth2tools-0.9.1.dist-info/top_level.txt
oauth2tools-0.9.1.dist-info/RECORD
