Metadata-Version: 2.1
Name: oauth2tools
Version: 0.9.1
Summary: A toolset for the most requirements dealing with OAuth2 and OpenID Connect.
Author: Andreas Rühl
Maintainer: Andreas Rühl
License: MIT
Project-URL: GitHub, https://github.com/aruehl/oauth2tools
Project-URL: Bug Tracker, https://github.com/aruehl/oauth2tools/issues
Keywords: OAuth2,OIDC,OpenID Connect,Tools,Helper
Classifier: Development Status :: 4 - Beta
Classifier: Programming Language :: Python :: 3
Classifier: License :: OSI Approved :: MIT License
Classifier: Operating System :: OS Independent
Requires-Python: >=3.7
License-File: LICENSE
Requires-Dist: cryptography
Requires-Dist: flask
Requires-Dist: requests
Requires-Dist: werkzeug
Requires-Dist: PyJWT
